odoo/addons/account_invoice_export_job/README.rst
odoo/addons/account_invoice_export_job/__init__.py
odoo/addons/account_invoice_export_job/__manifest__.py
odoo/addons/account_invoice_export_job/data/queue_job_data.xml
odoo/addons/account_invoice_export_job/i18n/account_invoice_export_job.pot
odoo/addons/account_invoice_export_job/i18n/it.po
odoo/addons/account_invoice_export_job/models/__init__.py
odoo/addons/account_invoice_export_job/models/account_move.py
odoo/addons/account_invoice_export_job/readme/CONTRIBUTORS.md
odoo/addons/account_invoice_export_job/readme/CREDITS.md
odoo/addons/account_invoice_export_job/readme/DESCRIPTION.md
odoo/addons/account_invoice_export_job/static/description/icon.png
odoo/addons/account_invoice_export_job/static/description/index.html
odoo/addons/account_invoice_export_job/tests/__init__.py
odoo/addons/account_invoice_export_job/tests/test_account_invoice_export_job.py
odoo/addons/account_invoice_export_job/views/message_template.xml
odoo_addon_account_invoice_export_job-18.0.1.0.0.2.dist-info/METADATA
odoo_addon_account_invoice_export_job-18.0.1.0.0.2.dist-info/WHEEL
odoo_addon_account_invoice_export_job-18.0.1.0.0.2.dist-info/top_level.txt
odoo_addon_account_invoice_export_job-18.0.1.0.0.2.dist-info/RECORD
